gw_mongo_database/__init__.py
gw_mongo_database/database.py
gw_mongo_database-0.5.6.dist-info/METADATA
gw_mongo_database-0.5.6.dist-info/WHEEL
gw_mongo_database-0.5.6.dist-info/RECORD
