Metadata-Version: 2.3
Name: gw-mongo-database
Version: 0.5.6
Summary: Mongo DB Functionality for GW Projects
Author: Chris Moore
Author-email: cmoore@guidewire.com
Requires-Python: >=3.13
Classifier: Programming Language :: Python :: 3
Classifier: Programming Language :: Python :: 3.13
Requires-Dist: gw-settings-management (>=0.5.0,<0.6.0)
Requires-Dist: pymongo (>=4.11.3,<5.0.0)
